MANIFEST.in
README.md
setup.cfg
setup.py
rbpy/__init__.py
rbpy/relay.py
rbpy.egg-info/PKG-INFO
rbpy.egg-info/SOURCES.txt
rbpy.egg-info/dependency_links.txt
rbpy.egg-info/requires.txt
rbpy.egg-info/top_level.txt
requirements/core.txt
requirements/dev.txt