Metadata-Version: 1.1
Name: rbpy
Version: 0.1.0
Summary: Python wrapper around the RelayBox API.
Home-page: https://github.com/mmaybeno/rbpy
Author: Matt Maybeno
Author-email: mmaybeno@gmail.com
License: BSD
Download-URL: https://bitbucket.org/relaybox/rbpy/get/master.tar.gz
Keywords: Relay Box
Platform: UNKNOWN
Classifier: Development Status :: 3 - Alpha
Classifier: Intended Audience :: Developers
Classifier: Programming Language :: Python :: 2.7
Classifier: Programming Language :: Python :: 3
